<?xml version="1.0" ?>
<Pokemon gameVersion="EoS">
  <Strings>
    <English>
      <Name>Trapinch</Name>
      <Category>Ant Pit</Category>
    </English>
  </Strings>
  <GenderedEntity>
    <PokeID>328</PokeID>
    <Unk31>225</Unk31>
    <PokedexNumber>328</PokedexNumber>
    <MovementSpeed>1</MovementSpeed>
    <SpriteIndex>525</SpriteIndex>
    <Gender>1</Gender>
    <BodySize>1</BodySize>
    <PrimaryType>9</PrimaryType>
    <SecondaryType>0</SecondaryType>
    <MovementType>0</MovementType>
    <IQGroup>3</IQGroup>
    <PrimaryAbility>9</PrimaryAbility>
    <SecondaryAbility>5</SecondaryAbility>
    <ExpYield>77</ExpYield>
    <RecruitRate1>82</RecruitRate1>
    <RecruitRate2>164</RecruitRate2>
    <Weight>153</Weight>
    <Size>19</Size>
    
    <ShadowSize>0</ShadowSize>
    <AsleepChance>8</AsleepChance>
    <HpRegen>100</HpRegen>
    <SpawnThreshold>0</SpawnThreshold>
    <BasePokemonIndex>356</BasePokemonIndex>
    <NoChestDropRate>800</NoChestDropRate>
    <NormalChestDropRate>15</NormalChestDropRate>
    <ExclusiveChestDropRate1>30</ExclusiveChestDropRate1>
    <ExclusiveChestDropRate2>10</ExclusiveChestDropRate2>
    <Personality>11</Personality>
    <EvolutionReq>
      <PreEvoIndex>0</PreEvoIndex>
      <Method>0</Method>
      <Param1>0</Param1>
      <Param2>0</Param2>
    </EvolutionReq>
    <BaseStats>
      <HP>30</HP>
      <Attack>15</Attack>
      <SpAttack>15</SpAttack>
      <Defense>7</Defense>
      <SpDefense>7</SpDefense>
    </BaseStats>
    <ExclusiveItems>
      <ItemID>0</ItemID>
      <ItemID>0</ItemID>
      <ItemID>0</ItemID>
      <ItemID>1250</ItemID>
    </ExclusiveItems>
    <Bitfield>
      
      
      
      
      <CanMove>1</CanMove>
      <CanThrowItems>1</CanThrowItems>
      <CanEvolve>1</CanEvolve>
      <ItemRequiredForSpawning>0</ItemRequiredForSpawning>
    </Bitfield>
  </GenderedEntity>
  <GenderedEntity>
    <PokeID>328</PokeID>
    <Unk31>225</Unk31>
    <PokedexNumber>328</PokedexNumber>
    <MovementSpeed>1</MovementSpeed>
    <SpriteIndex>525</SpriteIndex>
    <Gender>2</Gender>
    <BodySize>1</BodySize>
    <PrimaryType>9</PrimaryType>
    <SecondaryType>0</SecondaryType>
    <MovementType>0</MovementType>
    <IQGroup>3</IQGroup>
    <PrimaryAbility>9</PrimaryAbility>
    <SecondaryAbility>5</SecondaryAbility>
    <ExpYield>77</ExpYield>
    <RecruitRate1>82</RecruitRate1>
    <RecruitRate2>164</RecruitRate2>
    <Weight>153</Weight>
    <Size>19</Size>
    
    <ShadowSize>0</ShadowSize>
    <AsleepChance>8</AsleepChance>
    <HpRegen>100</HpRegen>
    <SpawnThreshold>0</SpawnThreshold>
    <BasePokemonIndex>356</BasePokemonIndex>
    <NoChestDropRate>800</NoChestDropRate>
    <NormalChestDropRate>15</NormalChestDropRate>
    <ExclusiveChestDropRate1>30</ExclusiveChestDropRate1>
    <ExclusiveChestDropRate2>10</ExclusiveChestDropRate2>
    <Personality>9</Personality>
    <EvolutionReq>
      <PreEvoIndex>0</PreEvoIndex>
      <Method>0</Method>
      <Param1>0</Param1>
      <Param2>0</Param2>
    </EvolutionReq>
    <BaseStats>
      <HP>30</HP>
      <Attack>15</Attack>
      <SpAttack>15</SpAttack>
      <Defense>7</Defense>
      <SpDefense>7</SpDefense>
    </BaseStats>
    <ExclusiveItems>
      <ItemID>0</ItemID>
      <ItemID>0</ItemID>
      <ItemID>0</ItemID>
      <ItemID>1250</ItemID>
    </ExclusiveItems>
    <Bitfield>
      
      
      
      
      <CanMove>1</CanMove>
      <CanThrowItems>1</CanThrowItems>
      <CanEvolve>1</CanEvolve>
      <ItemRequiredForSpawning>0</ItemRequiredForSpawning>
    </Bitfield>
  </GenderedEntity>
  <Moveset>
    <LevelUpMoves>
      <Learn>
        <Level>1</Level>
        <MoveID>63</MoveID>
      </Learn>
      <Learn>
        <Level>9</Level>
        <MoveID>142</MoveID>
      </Learn>
      <Learn>
        <Level>17</Level>
        <MoveID>167</MoveID>
      </Learn>
      <Learn>
        <Level>25</Level>
        <MoveID>143</MoveID>
      </Learn>
      <Learn>
        <Level>33</Level>
        <MoveID>62</MoveID>
      </Learn>
      <Learn>
        <Level>41</Level>
        <MoveID>8</MoveID>
      </Learn>
      <Learn>
        <Level>49</Level>
        <MoveID>141</MoveID>
      </Learn>
      <Learn>
        <Level>57</Level>
        <MoveID>242</MoveID>
      </Learn>
      <Learn>
        <Level>65</Level>
        <MoveID>484</MoveID>
      </Learn>
      <Learn>
        <Level>73</Level>
        <MoveID>118</MoveID>
      </Learn>
      <Learn>
        <Level>81</Level>
        <MoveID>516</MoveID>
      </Learn>
      <Learn>
        <Level>89</Level>
        <MoveID>131</MoveID>
      </Learn>
    </LevelUpMoves>
    <EggMoves>
      <MoveID>57</MoveID>
      <MoveID>74</MoveID>
      <MoveID>121</MoveID>
      <MoveID>190</MoveID>
      <MoveID>346</MoveID>
    </EggMoves>
    <HmTmMoves>
      <MoveID>8</MoveID>
      <MoveID>24</MoveID>
      <MoveID>29</MoveID>
      <MoveID>30</MoveID>
      <MoveID>48</MoveID>
      <MoveID>50</MoveID>
      <MoveID>56</MoveID>
      <MoveID>67</MoveID>
      <MoveID>73</MoveID>
      <MoveID>76</MoveID>
      <MoveID>104</MoveID>
      <MoveID>118</MoveID>
      <MoveID>141</MoveID>
      <MoveID>151</MoveID>
      <MoveID>197</MoveID>
      <MoveID>223</MoveID>
      <MoveID>227</MoveID>
      <MoveID>232</MoveID>
      <MoveID>242</MoveID>
      <MoveID>263</MoveID>
      <MoveID>301</MoveID>
      <MoveID>304</MoveID>
      <MoveID>324</MoveID>
      <MoveID>326</MoveID>
      <MoveID>328</MoveID>
      <MoveID>360</MoveID>
      <MoveID>394</MoveID>
      <MoveID>471</MoveID>
      <MoveID>534</MoveID>
    </HmTmMoves>
  </Moveset>
  <Moveset>
    <LevelUpMoves>
      <Learn>
        <Level>1</Level>
        <MoveID>63</MoveID>
      </Learn>
      <Learn>
        <Level>9</Level>
        <MoveID>142</MoveID>
      </Learn>
      <Learn>
        <Level>17</Level>
        <MoveID>167</MoveID>
      </Learn>
      <Learn>
        <Level>25</Level>
        <MoveID>143</MoveID>
      </Learn>
      <Learn>
        <Level>33</Level>
        <MoveID>62</MoveID>
      </Learn>
      <Learn>
        <Level>41</Level>
        <MoveID>8</MoveID>
      </Learn>
      <Learn>
        <Level>49</Level>
        <MoveID>141</MoveID>
      </Learn>
      <Learn>
        <Level>57</Level>
        <MoveID>242</MoveID>
      </Learn>
      <Learn>
        <Level>65</Level>
        <MoveID>484</MoveID>
      </Learn>
      <Learn>
        <Level>73</Level>
        <MoveID>118</MoveID>
      </Learn>
      <Learn>
        <Level>81</Level>
        <MoveID>516</MoveID>
      </Learn>
      <Learn>
        <Level>89</Level>
        <MoveID>131</MoveID>
      </Learn>
    </LevelUpMoves>
    <EggMoves>
      <MoveID>57</MoveID>
      <MoveID>74</MoveID>
      <MoveID>121</MoveID>
      <MoveID>190</MoveID>
      <MoveID>346</MoveID>
    </EggMoves>
    <HmTmMoves>
      <MoveID>8</MoveID>
      <MoveID>24</MoveID>
      <MoveID>29</MoveID>
      <MoveID>30</MoveID>
      <MoveID>48</MoveID>
      <MoveID>50</MoveID>
      <MoveID>56</MoveID>
      <MoveID>67</MoveID>
      <MoveID>73</MoveID>
      <MoveID>76</MoveID>
      <MoveID>104</MoveID>
      <MoveID>118</MoveID>
      <MoveID>141</MoveID>
      <MoveID>151</MoveID>
      <MoveID>197</MoveID>
      <MoveID>223</MoveID>
      <MoveID>227</MoveID>
      <MoveID>232</MoveID>
      <MoveID>242</MoveID>
      <MoveID>263</MoveID>
      <MoveID>301</MoveID>
      <MoveID>304</MoveID>
      <MoveID>324</MoveID>
      <MoveID>326</MoveID>
      <MoveID>328</MoveID>
      <MoveID>360</MoveID>
      <MoveID>394</MoveID>
      <MoveID>471</MoveID>
      <MoveID>534</MoveID>
    </HmTmMoves>
  </Moveset>
  <StatsGrowth>
    <Level>
      <RequiredExp>0</RequiredExp>
      <HP>0</HP>
      <Attack>0</Attack>
      <SpAttack>0</SpAttack>
      <Defense>0</Defense>
      <SpDefense>0</SpDefense>
    </Level>
    <Level>
      <RequiredExp>8</RequiredExp>
      <HP>3</HP>
      <Attack>1</Attack>
      <SpAttack>1</SpAttack>
      <Defense>1</Defense>
      <SpDefense>1</SpDefense>
    </Level>
    <Level>
      <RequiredExp>21</RequiredExp>
      <HP>3</HP>
      <Attack>1</Attack>
      <SpAttack>1</SpAttack>
      <Defense>0</Defense>
      <SpDefense>0</SpDefense>
    </Level>
    <Level>
      <RequiredExp>37</RequiredExp>
      <HP>3</HP>
      <Attack>0</Attack>
      <SpAttack>0</SpAttack>
      <Defense>1</Defense>
      <SpDefense>1</SpDefense>
    </Level>
    <Level>
      <RequiredExp>81</RequiredExp>
      <HP>3</HP>
      <Attack>1</Attack>
      <SpAttack>1</SpAttack>
      <Defense>0</Defense>
      <SpDefense>0</SpDefense>
    </Level>
    <Level>
      <RequiredExp>177</RequiredExp>
      <HP>3</HP>
      <Attack>0</Attack>
      <SpAttack>0</SpAttack>
      <Defense>1</Defense>
      <SpDefense>1</SpDefense>
    </Level>
    <Level>
      <RequiredExp>275</RequiredExp>
      <HP>3</HP>
      <Attack>1</Attack>
      <SpAttack>1</SpAttack>
      <Defense>0</Defense>
      <SpDefense>0</SpDefense>
    </Level>
    <Level>
      <RequiredExp>516</RequiredExp>
      <HP>3</HP>
      <Attack>1</Attack>
      <SpAttack>1</SpAttack>
      <Defense>1</Defense>
      <SpDefense>1</SpDefense>
    </Level>
    <Level>
      <RequiredExp>1040</RequiredExp>
      <HP>3</HP>
      <Attack>1</Attack>
      <SpAttack>1</SpAttack>
      <Defense>0</Defense>
      <SpDefense>0</SpDefense>
    </Level>
    <Level>
      <RequiredExp>1567</RequiredExp>
      <HP>1</HP>
      <Attack>1</Attack>
      <SpAttack>1</SpAttack>
      <Defense>1</Defense>
      <SpDefense>1</SpDefense>
    </Level>
    <Level>
      <RequiredExp>2396</RequiredExp>
      <HP>1</HP>
      <Attack>1</Attack>
      <SpAttack>1</SpAttack>
      <Defense>0</Defense>
      <SpDefense>0</SpDefense>
    </Level>
    <Level>
      <RequiredExp>4422</RequiredExp>
      <HP>1</HP>
      <Attack>1</Attack>
      <SpAttack>1</SpAttack>
      <Defense>1</Defense>
      <SpDefense>1</SpDefense>
    </Level>
    <Level>
      <RequiredExp>6452</RequiredExp>
      <HP>1</HP>
      <Attack>1</Attack>
      <SpAttack>1</SpAttack>
      <Defense>0</Defense>
      <SpDefense>0</SpDefense>
    </Level>
    <Level>
      <RequiredExp>10059</RequiredExp>
      <HP>1</HP>
      <Attack>1</Attack>
      <SpAttack>1</SpAttack>
      <Defense>0</Defense>
      <SpDefense>0</SpDefense>
    </Level>
    <Level>
      <RequiredExp>13670</RequiredExp>
      <HP>1</HP>
      <Attack>1</Attack>
      <SpAttack>1</SpAttack>
      <Defense>1</Defense>
      <SpDefense>1</SpDefense>
    </Level>
    <Level>
      <RequiredExp>17718</RequiredExp>
      <HP>1</HP>
      <Attack>1</Attack>
      <SpAttack>1</SpAttack>
      <Defense>1</Defense>
      <SpDefense>1</SpDefense>
    </Level>
    <Level>
      <RequiredExp>21771</RequiredExp>
      <HP>1</HP>
      <Attack>1</Attack>
      <SpAttack>1</SpAttack>
      <Defense>1</Defense>
      <SpDefense>1</SpDefense>
    </Level>
    <Level>
      <RequiredExp>26271</RequiredExp>
      <HP>1</HP>
      <Attack>1</Attack>
      <SpAttack>1</SpAttack>
      <Defense>1</Defense>
      <SpDefense>1</SpDefense>
    </Level>
    <Level>
      <RequiredExp>30776</RequiredExp>
      <HP>1</HP>
      <Attack>1</Attack>
      <SpAttack>1</SpAttack>
      <Defense>1</Defense>
      <SpDefense>1</SpDefense>
    </Level>
    <Level>
      <RequiredExp>35283</RequiredExp>
      <HP>1</HP>
      <Attack>1</Attack>
      <SpAttack>1</SpAttack>
      <Defense>1</Defense>
      <SpDefense>1</SpDefense>
    </Level>
    <Level>
      <RequiredExp>39824</RequiredExp>
      <HP>1</HP>
      <Attack>1</Attack>
      <SpAttack>1</SpAttack>
      <Defense>1</Defense>
      <SpDefense>1</SpDefense>
    </Level>
    <Level>
      <RequiredExp>45085</RequiredExp>
      <HP>1</HP>
      <Attack>1</Attack>
      <SpAttack>1</SpAttack>
      <Defense>1</Defense>
      <SpDefense>1</SpDefense>
    </Level>
    <Level>
      <RequiredExp>50350</RequiredExp>
      <HP>1</HP>
      <Attack>1</Attack>
      <SpAttack>1</SpAttack>
      <Defense>1</Defense>
      <SpDefense>1</SpDefense>
    </Level>
    <Level>
      <RequiredExp>55622</RequiredExp>
      <HP>1</HP>
      <Attack>1</Attack>
      <SpAttack>1</SpAttack>
      <Defense>1</Defense>
      <SpDefense>1</SpDefense>
    </Level>
    <Level>
      <RequiredExp>62334</RequiredExp>
      <HP>1</HP>
      <Attack>1</Attack>
      <SpAttack>1</SpAttack>
      <Defense>1</Defense>
      <SpDefense>1</SpDefense>
    </Level>
    <Level>
      <RequiredExp>70499</RequiredExp>
      <HP>1</HP>
      <Attack>1</Attack>
      <SpAttack>1</SpAttack>
      <Defense>1</Defense>
      <SpDefense>1</SpDefense>
    </Level>
    <Level>
      <RequiredExp>79384</RequiredExp>
      <HP>1</HP>
      <Attack>1</Attack>
      <SpAttack>1</SpAttack>
      <Defense>1</Defense>
      <SpDefense>1</SpDefense>
    </Level>
    <Level>
      <RequiredExp>88989</RequiredExp>
      <HP>1</HP>
      <Attack>1</Attack>
      <SpAttack>1</SpAttack>
      <Defense>1</Defense>
      <SpDefense>1</SpDefense>
    </Level>
    <Level>
      <RequiredExp>99314</RequiredExp>
      <HP>3</HP>
      <Attack>3</Attack>
      <SpAttack>3</SpAttack>
      <Defense>3</Defense>
      <SpDefense>3</SpDefense>
    </Level>
    <Level>
      <RequiredExp>110358</RequiredExp>
      <HP>3</HP>
      <Attack>3</Attack>
      <SpAttack>3</SpAttack>
      <Defense>3</Defense>
      <SpDefense>3</SpDefense>
    </Level>
    <Level>
      <RequiredExp>122123</RequiredExp>
      <HP>3</HP>
      <Attack>3</Attack>
      <SpAttack>3</SpAttack>
      <Defense>3</Defense>
      <SpDefense>3</SpDefense>
    </Level>
    <Level>
      <RequiredExp>134607</RequiredExp>
      <HP>2</HP>
      <Attack>2</Attack>
      <SpAttack>2</SpAttack>
      <Defense>2</Defense>
      <SpDefense>2</SpDefense>
    </Level>
    <Level>
      <RequiredExp>149262</RequiredExp>
      <HP>2</HP>
      <Attack>2</Attack>
      <SpAttack>2</SpAttack>
      <Defense>2</Defense>
      <SpDefense>2</SpDefense>
    </Level>
    <Level>
      <RequiredExp>164636</RequiredExp>
      <HP>2</HP>
      <Attack>2</Attack>
      <SpAttack>2</SpAttack>
      <Defense>2</Defense>
      <SpDefense>2</SpDefense>
    </Level>
    <Level>
      <RequiredExp>180729</RequiredExp>
      <HP>2</HP>
      <Attack>1</Attack>
      <SpAttack>1</SpAttack>
      <Defense>1</Defense>
      <SpDefense>1</SpDefense>
    </Level>
    <Level>
      <RequiredExp>197543</RequiredExp>
      <HP>2</HP>
      <Attack>1</Attack>
      <SpAttack>1</SpAttack>
      <Defense>1</Defense>
      <SpDefense>1</SpDefense>
    </Level>
    <Level>
      <RequiredExp>215076</RequiredExp>
      <HP>2</HP>
      <Attack>1</Attack>
      <SpAttack>1</SpAttack>
      <Defense>1</Defense>
      <SpDefense>1</SpDefense>
    </Level>
    <Level>
      <RequiredExp>233329</RequiredExp>
      <HP>2</HP>
      <Attack>1</Attack>
      <SpAttack>1</SpAttack>
      <Defense>1</Defense>
      <SpDefense>1</SpDefense>
    </Level>
    <Level>
      <RequiredExp>252302</RequiredExp>
      <HP>2</HP>
      <Attack>1</Attack>
      <SpAttack>1</SpAttack>
      <Defense>1</Defense>
      <SpDefense>1</SpDefense>
    </Level>
    <Level>
      <RequiredExp>271995</RequiredExp>
      <HP>2</HP>
      <Attack>1</Attack>
      <SpAttack>1</SpAttack>
      <Defense>1</Defense>
      <SpDefense>1</SpDefense>
    </Level>
    <Level>
      <RequiredExp>292408</RequiredExp>
      <HP>2</HP>
      <Attack>1</Attack>
      <SpAttack>1</SpAttack>
      <Defense>1</Defense>
      <SpDefense>1</SpDefense>
    </Level>
    <Level>
      <RequiredExp>313540</RequiredExp>
      <HP>2</HP>
      <Attack>1</Attack>
      <SpAttack>1</SpAttack>
      <Defense>0</Defense>
      <SpDefense>1</SpDefense>
    </Level>
    <Level>
      <RequiredExp>335392</RequiredExp>
      <HP>2</HP>
      <Attack>1</Attack>
      <SpAttack>0</SpAttack>
      <Defense>1</Defense>
      <SpDefense>0</SpDefense>
    </Level>
    <Level>
      <RequiredExp>358683</RequiredExp>
      <HP>2</HP>
      <Attack>0</Attack>
      <SpAttack>1</SpAttack>
      <Defense>0</Defense>
      <SpDefense>1</SpDefense>
    </Level>
    <Level>
      <RequiredExp>383414</RequiredExp>
      <HP>2</HP>
      <Attack>1</Attack>
      <SpAttack>0</SpAttack>
      <Defense>1</Defense>
      <SpDefense>0</SpDefense>
    </Level>
    <Level>
      <RequiredExp>409585</RequiredExp>
      <HP>1</HP>
      <Attack>0</Attack>
      <SpAttack>1</SpAttack>
      <Defense>0</Defense>
      <SpDefense>1</SpDefense>
    </Level>
    <Level>
      <RequiredExp>437195</RequiredExp>
      <HP>1</HP>
      <Attack>1</Attack>
      <SpAttack>0</SpAttack>
      <Defense>1</Defense>
      <SpDefense>0</SpDefense>
    </Level>
    <Level>
      <RequiredExp>466244</RequiredExp>
      <HP>1</HP>
      <Attack>0</Attack>
      <SpAttack>1</SpAttack>
      <Defense>0</Defense>
      <SpDefense>1</SpDefense>
    </Level>
    <Level>
      <RequiredExp>496734</RequiredExp>
      <HP>1</HP>
      <Attack>1</Attack>
      <SpAttack>0</SpAttack>
      <Defense>1</Defense>
      <SpDefense>0</SpDefense>
    </Level>
    <Level>
      <RequiredExp>528662</RequiredExp>
      <HP>1</HP>
      <Attack>0</Attack>
      <SpAttack>1</SpAttack>
      <Defense>0</Defense>
      <SpDefense>1</SpDefense>
    </Level>
    <Level>
      <RequiredExp>562031</RequiredExp>
      <HP>0</HP>
      <Attack>1</Attack>
      <SpAttack>0</SpAttack>
      <Defense>1</Defense>
      <SpDefense>0</SpDefense>
    </Level>
    <Level>
      <RequiredExp>596839</RequiredExp>
      <HP>1</HP>
      <Attack>0</Attack>
      <SpAttack>1</SpAttack>
      <Defense>0</Defense>
      <SpDefense>1</SpDefense>
    </Level>
    <Level>
      <RequiredExp>632835</RequiredExp>
      <HP>0</HP>
      <Attack>1</Attack>
      <SpAttack>0</SpAttack>
      <Defense>1</Defense>
      <SpDefense>0</SpDefense>
    </Level>
    <Level>
      <RequiredExp>668837</RequiredExp>
      <HP>1</HP>
      <Attack>0</Attack>
      <SpAttack>1</SpAttack>
      <Defense>0</Defense>
      <SpDefense>1</SpDefense>
    </Level>
    <Level>
      <RequiredExp>704847</RequiredExp>
      <HP>0</HP>
      <Attack>1</Attack>
      <SpAttack>0</SpAttack>
      <Defense>1</Defense>
      <SpDefense>0</SpDefense>
    </Level>
    <Level>
      <RequiredExp>740864</RequiredExp>
      <HP>1</HP>
      <Attack>0</Attack>
      <SpAttack>1</SpAttack>
      <Defense>0</Defense>
      <SpDefense>1</SpDefense>
    </Level>
    <Level>
      <RequiredExp>776889</RequiredExp>
      <HP>0</HP>
      <Attack>1</Attack>
      <SpAttack>0</SpAttack>
      <Defense>1</Defense>
      <SpDefense>0</SpDefense>
    </Level>
    <Level>
      <RequiredExp>812921</RequiredExp>
      <HP>1</HP>
      <Attack>0</Attack>
      <SpAttack>1</SpAttack>
      <Defense>0</Defense>
      <SpDefense>1</SpDefense>
    </Level>
    <Level>
      <RequiredExp>848959</RequiredExp>
      <HP>0</HP>
      <Attack>1</Attack>
      <SpAttack>0</SpAttack>
      <Defense>1</Defense>
      <SpDefense>0</SpDefense>
    </Level>
    <Level>
      <RequiredExp>885006</RequiredExp>
      <HP>1</HP>
      <Attack>1</Attack>
      <SpAttack>1</SpAttack>
      <Defense>1</Defense>
      <SpDefense>1</SpDefense>
    </Level>
    <Level>
      <RequiredExp>921059</RequiredExp>
      <HP>1</HP>
      <Attack>1</Attack>
      <SpAttack>1</SpAttack>
      <Defense>1</Defense>
      <SpDefense>1</SpDefense>
    </Level>
    <Level>
      <RequiredExp>957119</RequiredExp>
      <HP>1</HP>
      <Attack>1</Attack>
      <SpAttack>1</SpAttack>
      <Defense>1</Defense>
      <SpDefense>1</SpDefense>
    </Level>
    <Level>
      <RequiredExp>993187</RequiredExp>
      <HP>1</HP>
      <Attack>1</Attack>
      <SpAttack>1</SpAttack>
      <Defense>1</Defense>
      <SpDefense>1</SpDefense>
    </Level>
    <Level>
      <RequiredExp>1029262</RequiredExp>
      <HP>1</HP>
      <Attack>1</Attack>
      <SpAttack>1</SpAttack>
      <Defense>1</Defense>
      <SpDefense>1</SpDefense>
    </Level>
    <Level>
      <RequiredExp>1065344</RequiredExp>
      <HP>1</HP>
      <Attack>1</Attack>
      <SpAttack>1</SpAttack>
      <Defense>1</Defense>
      <SpDefense>1</SpDefense>
    </Level>
    <Level>
      <RequiredExp>1101433</RequiredExp>
      <HP>1</HP>
      <Attack>1</Attack>
      <SpAttack>1</SpAttack>
      <Defense>1</Defense>
      <SpDefense>1</SpDefense>
    </Level>
    <Level>
      <RequiredExp>1137530</RequiredExp>
      <HP>1</HP>
      <Attack>1</Attack>
      <SpAttack>1</SpAttack>
      <Defense>1</Defense>
      <SpDefense>1</SpDefense>
    </Level>
    <Level>
      <RequiredExp>1173633</RequiredExp>
      <HP>1</HP>
      <Attack>1</Attack>
      <SpAttack>1</SpAttack>
      <Defense>1</Defense>
      <SpDefense>1</SpDefense>
    </Level>
    <Level>
      <RequiredExp>1209743</RequiredExp>
      <HP>1</HP>
      <Attack>1</Attack>
      <SpAttack>1</SpAttack>
      <Defense>1</Defense>
      <SpDefense>1</SpDefense>
    </Level>
    <Level>
      <RequiredExp>1245862</RequiredExp>
      <HP>1</HP>
      <Attack>1</Attack>
      <SpAttack>1</SpAttack>
      <Defense>1</Defense>
      <SpDefense>1</SpDefense>
    </Level>
    <Level>
      <RequiredExp>1281987</RequiredExp>
      <HP>1</HP>
      <Attack>1</Attack>
      <SpAttack>1</SpAttack>
      <Defense>1</Defense>
      <SpDefense>1</SpDefense>
    </Level>
    <Level>
      <RequiredExp>1318119</RequiredExp>
      <HP>1</HP>
      <Attack>1</Attack>
      <SpAttack>1</SpAttack>
      <Defense>1</Defense>
      <SpDefense>1</SpDefense>
    </Level>
    <Level>
      <RequiredExp>1354259</RequiredExp>
      <HP>1</HP>
      <Attack>1</Attack>
      <SpAttack>1</SpAttack>
      <Defense>1</Defense>
      <SpDefense>1</SpDefense>
    </Level>
    <Level>
      <RequiredExp>1390406</RequiredExp>
      <HP>1</HP>
      <Attack>1</Attack>
      <SpAttack>1</SpAttack>
      <Defense>1</Defense>
      <SpDefense>1</SpDefense>
    </Level>
    <Level>
      <RequiredExp>1426560</RequiredExp>
      <HP>1</HP>
      <Attack>1</Attack>
      <SpAttack>1</SpAttack>
      <Defense>1</Defense>
      <SpDefense>1</SpDefense>
    </Level>
    <Level>
      <RequiredExp>1462721</RequiredExp>
      <HP>1</HP>
      <Attack>1</Attack>
      <SpAttack>1</SpAttack>
      <Defense>1</Defense>
      <SpDefense>1</SpDefense>
    </Level>
    <Level>
      <RequiredExp>1498889</RequiredExp>
      <HP>1</HP>
      <Attack>1</Attack>
      <SpAttack>1</SpAttack>
      <Defense>1</Defense>
      <SpDefense>1</SpDefense>
    </Level>
    <Level>
      <RequiredExp>1535065</RequiredExp>
      <HP>1</HP>
      <Attack>1</Attack>
      <SpAttack>1</SpAttack>
      <Defense>1</Defense>
      <SpDefense>1</SpDefense>
    </Level>
    <Level>
      <RequiredExp>1571248</RequiredExp>
      <HP>1</HP>
      <Attack>1</Attack>
      <SpAttack>1</SpAttack>
      <Defense>1</Defense>
      <SpDefense>1</SpDefense>
    </Level>
    <Level>
      <RequiredExp>1607438</RequiredExp>
      <HP>1</HP>
      <Attack>1</Attack>
      <SpAttack>1</SpAttack>
      <Defense>1</Defense>
      <SpDefense>1</SpDefense>
    </Level>
    <Level>
      <RequiredExp>1643635</RequiredExp>
      <HP>1</HP>
      <Attack>1</Attack>
      <SpAttack>1</SpAttack>
      <Defense>1</Defense>
      <SpDefense>1</SpDefense>
    </Level>
    <Level>
      <RequiredExp>1679839</RequiredExp>
      <HP>1</HP>
      <Attack>1</Attack>
      <SpAttack>1</SpAttack>
      <Defense>1</Defense>
      <SpDefense>1</SpDefense>
    </Level>
    <Level>
      <RequiredExp>1716051</RequiredExp>
      <HP>1</HP>
      <Attack>1</Attack>
      <SpAttack>1</SpAttack>
      <Defense>1</Defense>
      <SpDefense>1</SpDefense>
    </Level>
    <Level>
      <RequiredExp>1752270</RequiredExp>
      <HP>1</HP>
      <Attack>1</Attack>
      <SpAttack>1</SpAttack>
      <Defense>1</Defense>
      <SpDefense>1</SpDefense>
    </Level>
    <Level>
      <RequiredExp>1788496</RequiredExp>
      <HP>1</HP>
      <Attack>1</Attack>
      <SpAttack>1</SpAttack>
      <Defense>1</Defense>
      <SpDefense>1</SpDefense>
    </Level>
    <Level>
      <RequiredExp>1824729</RequiredExp>
      <HP>1</HP>
      <Attack>1</Attack>
      <SpAttack>1</SpAttack>
      <Defense>1</Defense>
      <SpDefense>1</SpDefense>
    </Level>
    <Level>
      <RequiredExp>1860969</RequiredExp>
      <HP>1</HP>
      <Attack>1</Attack>
      <SpAttack>1</SpAttack>
      <Defense>1</Defense>
      <SpDefense>1</SpDefense>
    </Level>
    <Level>
      <RequiredExp>1897217</RequiredExp>
      <HP>1</HP>
      <Attack>1</Attack>
      <SpAttack>1</SpAttack>
      <Defense>1</Defense>
      <SpDefense>1</SpDefense>
    </Level>
    <Level>
      <RequiredExp>1933472</RequiredExp>
      <HP>1</HP>
      <Attack>1</Attack>
      <SpAttack>1</SpAttack>
      <Defense>1</Defense>
      <SpDefense>1</SpDefense>
    </Level>
    <Level>
      <RequiredExp>1969733</RequiredExp>
      <HP>1</HP>
      <Attack>1</Attack>
      <SpAttack>1</SpAttack>
      <Defense>1</Defense>
      <SpDefense>1</SpDefense>
    </Level>
    <Level>
      <RequiredExp>2006003</RequiredExp>
      <HP>1</HP>
      <Attack>1</Attack>
      <SpAttack>1</SpAttack>
      <Defense>1</Defense>
      <SpDefense>1</SpDefense>
    </Level>
    <Level>
      <RequiredExp>2042280</RequiredExp>
      <HP>1</HP>
      <Attack>1</Attack>
      <SpAttack>1</SpAttack>
      <Defense>1</Defense>
      <SpDefense>1</SpDefense>
    </Level>
    <Level>
      <RequiredExp>2078563</RequiredExp>
      <HP>1</HP>
      <Attack>1</Attack>
      <SpAttack>1</SpAttack>
      <Defense>1</Defense>
      <SpDefense>1</SpDefense>
    </Level>
    <Level>
      <RequiredExp>2114854</RequiredExp>
      <HP>1</HP>
      <Attack>1</Attack>
      <SpAttack>1</SpAttack>
      <Defense>1</Defense>
      <SpDefense>1</SpDefense>
    </Level>
    <Level>
      <RequiredExp>2151152</RequiredExp>
      <HP>1</HP>
      <Attack>1</Attack>
      <SpAttack>1</SpAttack>
      <Defense>1</Defense>
      <SpDefense>1</SpDefense>
    </Level>
    <Level>
      <RequiredExp>2187457</RequiredExp>
      <HP>1</HP>
      <Attack>1</Attack>
      <SpAttack>1</SpAttack>
      <Defense>1</Defense>
      <SpDefense>1</SpDefense>
    </Level>
    <Level>
      <RequiredExp>2223769</RequiredExp>
      <HP>1</HP>
      <Attack>1</Attack>
      <SpAttack>1</SpAttack>
      <Defense>1</Defense>
      <SpDefense>1</SpDefense>
    </Level>
    <Level>
      <RequiredExp>2260089</RequiredExp>
      <HP>1</HP>
      <Attack>1</Attack>
      <SpAttack>1</SpAttack>
      <Defense>1</Defense>
      <SpDefense>1</SpDefense>
    </Level>
    <Level>
      <RequiredExp>2296416</RequiredExp>
      <HP>1</HP>
      <Attack>1</Attack>
      <SpAttack>1</SpAttack>
      <Defense>1</Defense>
      <SpDefense>1</SpDefense>
    </Level>
    <Level>
      <RequiredExp>2332792</RequiredExp>
      <HP>1</HP>
      <Attack>1</Attack>
      <SpAttack>1</SpAttack>
      <Defense>1</Defense>
      <SpDefense>1</SpDefense>
    </Level>
  </StatsGrowth>
  <Portraits>
    <Portrait>
      <At4pxImage>QVQ0UFiFAgsOAwQHCAoMDSADB7a2H/xf+B/waGho+GiGhoaGuLgf8C8f7A/YJrYmMWZG/zF3aBR1d0ZRK7cP+XcfwEahETGrpbruuqof/O6u6Krq577ut7cfoP8RMmRmel4TY//qflcR7n53V2sP51d+txW391FXn4BkD3NBD28VZGj+aFGBhoYfHx9+bx96iDgPdBiJiYn7I5iYmFG5mXFtuTl/uRk1D3l3oXIPl3Ufkx+PH4sPh1N7tycxdXcPnHclW7dXD1JXcbclfz8P/A/V8XdTd1F37yVRcg/EH3Uf8vRRd1cTb77nD0gPRL/nH/zu9xGEiFf/H4OIdzWBiHf+V4GJ7n6RmA/8r5m+kR/8mbm5GfsVm5sbg7sbFV8P/DUP+FXLyxtf97y8PF+8nFEY/3N3Fd1zdyUd83N38jG3D5dXcfh1FSFzVQ9PtQ9mwCNzD2FvhB7NHslf+A69Qh94dx60H2gerZ8WVb7/sbnuXpGb7vf/srt3F7S7dxX/ubtXI8vLVUHzvLz1wby8zPFXD/oTD/YSvBwzzP+cMf/MG/NVzPwUX1W8MV+1D3tVH/pTD/YxD/ITD/f1dh/oLxEztS8RHjwCH9sf11/4H8u/vyFDKw/gb+I1D7MjtR/C/1U/IcwzEcnM2hFDvBXEvCMPeYfCL3UvcC9rX/FMIVP/9UzSMi9MIh3/0kwx0iQU9UL/MjJXE1NRdxP/dXN3MXf/VfV9g19VH03ytdK/JLUjLV9VNUL/cndV0vJ3VyO/JB9JEzH/PzEff7EjVSVVQ3Uq/3fTp1I3HadS/iMdJTPUMSMPgKshD3wkD3gSD3QxQV+8dQ/rdTfCzF+AVw9f/2hfZS7D</At4pxImage>
      <Palette>AP8AOi0jWkc6j1s7mLCw2YFWd8fX9qJmj8/Hr9e3/8igz+e35/e3////9ax4tmo1</Palette>
    </Portrait>
    <Portrait/>
    <Portrait/>
    <Portrait/>
    <Portrait/>
    <Portrait/>
    <Portrait/>
    <Portrait/>
    <Portrait/>
    <Portrait/>
    <Portrait/>
    <Portrait/>
    <Portrait/>
    <Portrait/>
    <Portrait/>
    <Portrait/>
    <Portrait/>
    <Portrait/>
    <Portrait/>
    <Portrait/>
    <Portrait/>
    <Portrait/>
    <Portrait/>
    <Portrait/>
    <Portrait/>
    <Portrait/>
    <Portrait/>
    <Portrait/>
    <Portrait/>
    <Portrait/>
    <Portrait/>
    <Portrait/>
    <Portrait/>
    <Portrait/>
    <Portrait/>
    <Portrait/>
    <Portrait/>
    <Portrait/>
    <Portrait/>
    <Portrait/>
  </Portraits>
  <Portraits>
    <Portrait/>
    <Portrait/>
    <Portrait/>
    <Portrait/>
    <Portrait/>
    <Portrait/>
    <Portrait/>
    <Portrait/>
    <Portrait/>
    <Portrait/>
    <Portrait/>
    <Portrait/>
    <Portrait/>
    <Portrait/>
    <Portrait/>
    <Portrait/>
    <Portrait/>
    <Portrait/>
    <Portrait/>
    <Portrait/>
    <Portrait/>
    <Portrait/>
    <Portrait/>
    <Portrait/>
    <Portrait/>
    <Portrait/>
    <Portrait/>
    <Portrait/>
    <Portrait/>
    <Portrait/>
    <Portrait/>
    <Portrait/>
    <Portrait/>
    <Portrait/>
    <Portrait/>
    <Portrait/>
    <Portrait/>
    <Portrait/>
    <Portrait/>
    <Portrait/>
  </Portraits>
</Pokemon>
